poweredge_fan/__init__.py
poweredge_fan/poweredge_fan.py
poweredge_fan/hardware/__init__.py
poweredge_fan/hardware/poweredge.py
poweredge_fan/hardware/sensors.py
poweredge_fan-1.0.4.dist-info/entry_points.txt
poweredge_fan-1.0.4.dist-info/WHEEL
poweredge_fan-1.0.4.dist-info/METADATA
poweredge_fan-1.0.4.dist-info/RECORD
