Metadata-Version: 2.1
Name: poweredge_fan
Version: 1.0.4
Summary: PyPowerEdgeFan is a Python-based PID fan controller for Dell PowerEdge servers.
Author-email: Jackie Yang <jackie@jackieyang.me>
Classifier: License :: OSI Approved :: MIT License
Classifier: Programming Language :: Python :: 3
Requires-Dist: PySensors
Project-URL: Source, https://github.com/valkjsaaa/PyPowerEdgeFan
